[
    {
        "id": "001",
        "name": "Espada Sagrada Arcaica",
        "cover": "/public/pages/assets/8474.png",
        "description": "A espada sagrada de um antigo guerreiro em batalha, ah um nome cravado nela.",
        "price": "1000",
        "update": "23/08/2024",
        "status": "Pendente",
        "quality": "Incomum"
    },
    {
        "id": "002",
        "name": "Medo Espreitador do Abismo",
        "cover": "/public/pages/assets/34401.png",
        "description": "Um arco que dispara flechas estelares.",
        "price": "27",
        "update": "24/08/2024",
        "status": "Pendente",
        "quality": "Sagrado"
    },
    {
        "id": "003",
        "name": "Montaria Espreitador do Abismo",
      "cover": "/public/pages/assets/34401.png",
      "description": "Um arco que dispara flechas estelares.",
      "price": "2700",
      "update": "24/08/2024",
      "status": "Verificado",
      "quality": "Sagrado",
      "category": "montaria"
    }
]